{
  "posts": [
    {
      "id": 1,
      "name": "test"
    }
  ],
  "profile":  {
    "key": "example-add-on",
    "name": "Example Add-on",
    "description": "An example add-on for Bitbucket",
    "vendor": {
      "name": "Angry Nerds",
      "url": "https://www.atlassian.com/angrynerds"
    },
    "baseUrl": "https://c652c18b.ngrok.io",
    "authentication": {
      "type": "jwt"
    },
    "lifecycle": {
      "installed": "/installed",
      "uninstalled": "/uninstalled"
    },
    "modules": {
      "oauthConsumer": {
        "clientId": "your_consumer_key"
      },
      "webhooks": [
        {
          "event": "*",
          "url": "/webhook"
        }
      ],
      "webItem": [
        {
          "url": "http://example.com?repoPath={repo_path}",
          "name": {
            "value": "Example Web Item"
          },
          "location": "org.bitbucket.repository.navigation",
          "key": "example-web-item",
          "params": {
            "auiIcon": "aui-iconfont-link"
          }
        }
      ],
      "repoPage": [
        {
          "url": "/connect-example?repoPath={repo_path}",
          "name": {
            "value": "Example Page"
          },
          "location": "org.bitbucket.repository.navigation",
          "key": "example-repo-page",
          "params": {
            "auiIcon": "aui-iconfont-doc"
          }
        }
      ],
      "webPanel": [
        {
          "url": "/connect-example?repoPath={repo_path}",
          "name": {
            "value": "Example Web Panel"
          },
          "location": "org.bitbucket.repository.overview.informationPanel",
          "key": "example-web-panel"
        }
      ]
    },
    "scopes": [
      "READ",
      "WRITE"
    ]
  }
}
